wh_lookml_gen/__init__.py
wh_lookml_gen/cli.py
wh_lookml_gen/config.py
wh_lookml_gen/dbt_test_gen.py
wh_lookml_gen/schema_cli.py
wh_lookml_gen/warehouse_target.py
wh_lookml_gen/wh_init_cli.py
wh_lookml_gen/wh_lookml_gen.py
wh_lookml_gen/wh_lookml_gen_init.py
wh_lookml_gen-0.2.6.dist-info/AUTHORS.rst
wh_lookml_gen-0.2.6.dist-info/LICENSE
wh_lookml_gen-0.2.6.dist-info/METADATA
wh_lookml_gen-0.2.6.dist-info/WHEEL
wh_lookml_gen-0.2.6.dist-info/entry_points.txt
wh_lookml_gen-0.2.6.dist-info/top_level.txt
wh_lookml_gen-0.2.6.dist-info/RECORD
