Metadata-Version: 2.1
Name: wh-lookml-gen
Version: 0.2.6
Summary: generates lookml from a warehouse
Home-page: https://github.com/lewischarlesbaker/wh_lookml_gen
Author: Lewis Baker
Author-email: lewischarlebaker@gmail.com
License: MIT license
Keywords: wh_lookml_gen
Platform: UNKNOWN
Classifier: Development Status :: 2 - Pre-Alpha
Classifier: Intended Audience :: Developers
Classifier: License :: OSI Approved :: MIT License
Classifier: Natural Language :: English
Classifier: Programming Language :: Python :: 3
Classifier: Programming Language :: Python :: 3.6
Classifier: Programming Language :: Python :: 3.7
Classifier: Programming Language :: Python :: 3.8
Requires-Python: >=3.6
Requires-Dist: lkml (==1.1.0)
Requires-Dist: pandas-gbq (==0.15.0)
Requires-Dist: pandas (==1.3.1)
Requires-Dist: click (==8.0.1)
Requires-Dist: GitPython (==3.1.18)
Requires-Dist: protobuf (==3.17.3)
Requires-Dist: PyYAML (==5.4.1)
Requires-Dist: ruamel.base (==1.0.0)
